reprounzip-1.3.2-py3.12-nspkg.pth
reprounzip/common.py
reprounzip/main.py
reprounzip/orderedset.py
reprounzip/pack_info.py
reprounzip/parameters.py
reprounzip/signals.py
reprounzip/utils.py
reprounzip/plugins/__init__.py
reprounzip/unpackers/default.py
reprounzip/unpackers/graph.py
reprounzip/unpackers/provviewer.py
reprounzip/unpackers/common/__init__.py
reprounzip/unpackers/common/misc.py
reprounzip/unpackers/common/packages.py
reprounzip/unpackers/common/x11.py
reprounzip-1.3.2.dist-info/licenses/LICENSE.txt
reprounzip-1.3.2.dist-info/METADATA
reprounzip-1.3.2.dist-info/WHEEL
reprounzip-1.3.2.dist-info/entry_points.txt
reprounzip-1.3.2.dist-info/namespace_packages.txt
reprounzip-1.3.2.dist-info/top_level.txt
reprounzip-1.3.2.dist-info/RECORD
