Metadata-Version: 2.4
Name: reprounzip
Version: 1.3.2
Summary: Linux tool enabling reproducible experiments (unpacker)
Home-page: https://www.reprozip.org/
Author: Remi Rampin, Fernando Chirigati, Dennis Shasha, Juliana Freire
Author-email: reprozip@nyu.edu
Maintainer: Remi Rampin
Maintainer-email: remi@rampin.org
License: BSD-3-Clause
Project-URL: Documentation, https://docs.reprozip.org/
Project-URL: Examples, https://examples.reprozip.org/
Project-URL: Source, https://github.com/VIDA-NYU/reprozip
Project-URL: Bug Tracker, https://github.com/VIDA-NYU/reprozip/issues
Project-URL: Chat, https://riot.im/app/#/room/#reprozip:matrix.org
Project-URL: Changelog, https://github.com/VIDA-NYU/reprozip/blob/1.x/CHANGELOG.md
Keywords: reprozip,reprounzip,reproducibility,provenance,vida,nyu
Classifier: Development Status :: 5 - Production/Stable
Classifier: Intended Audience :: Science/Research
Classifier: License :: OSI Approved :: BSD License
Classifier: Programming Language :: Python :: 2.7
Classifier: Programming Language :: Python :: 3
Classifier: Topic :: Scientific/Engineering
Classifier: Topic :: System :: Archiving
License-File: LICENSE.txt
Requires-Dist: importlib-metadata
Requires-Dist: PyYAML
Requires-Dist: rpaths>=0.8
Requires-Dist: usagestats>=0.3
Requires-Dist: requests
Requires-Dist: distro
Requires-Dist: pyelftools
Provides-Extra: all
Requires-Dist: reprounzip-vagrant>=1.0; extra == "all"
Requires-Dist: reprounzip-docker>=1.0; extra == "all"
Requires-Dist: reprounzip-vistrails>=1.0; extra == "all"
Dynamic: author
Dynamic: author-email
Dynamic: classifier
Dynamic: description
Dynamic: home-page
Dynamic: keywords
Dynamic: license
Dynamic: license-file
Dynamic: maintainer
Dynamic: maintainer-email
Dynamic: project-url
Dynamic: provides-extra
Dynamic: requires-dist
Dynamic: summary
